mlops_lessons/__init__.py
mlops_lessons/version.py
mlops_lessons/jobs/__init__.py
mlops_lessons/jobs/training/__init__.py
mlops_lessons/jobs/training/main.py
mlops_lessons-1.0.0.dist-info/METADATA
mlops_lessons-1.0.0.dist-info/WHEEL
mlops_lessons-1.0.0.dist-info/entry_points.txt
mlops_lessons-1.0.0.dist-info/top_level.txt
mlops_lessons-1.0.0.dist-info/RECORD
